agilemind/__init__.py
agilemind/agile.py
agilemind/fixed.py
agilemind/main.py
agilemind/waterfall.py
agilemind/checker/__init__.py
agilemind/checker/checker_pipeline.py
agilemind/checker/interface.py
agilemind/checker/static_checking.py
agilemind/checker/python/__init__.py
agilemind/checker/python/attribute_checker.py
agilemind/checker/python/import_checker.py
agilemind/checker/python/pylint_checker.py
agilemind/checker/python/syntax_checker.py
agilemind/checker/web/__init__.py
agilemind/checker/web/css_validator.py
agilemind/checker/web/html_validator.py
agilemind/checker/web/js_validator.py
agilemind/checker/web/web_checker.py
agilemind/context/__init__.py
agilemind/context/context.py
agilemind/context/cost.py
agilemind/context/message_queue.py
agilemind/context/token_usage.py
agilemind/execution/__init__.py
agilemind/execution/agent.py
agilemind/execution/config.py
agilemind/execution/executor.py
agilemind/execution/multimodal.py
agilemind/execution/runner.py
agilemind/pipeline/__init__.py
agilemind/pipeline/pipeline.py
agilemind/prompt/__init__.py
agilemind/prompt/agile.py
agilemind/prompt/fixed.py
agilemind/prompt/flow.py
agilemind/prompt/waterfall.py
agilemind/stage/__init__.py
agilemind/stage/definition.py
agilemind/task/__init__.py
agilemind/task/definition.py
agilemind/task/utils.py
agilemind/tool/__init__.py
agilemind/tool/group.py
agilemind/tool/tool_decorator.py
agilemind/tool/tools.py
agilemind/tool/utils.py
agilemind/utils/__init__.py
agilemind/utils/code_framework_extractor.py
agilemind/utils/config_loader.py
agilemind/utils/cost.py
agilemind/utils/file.py
agilemind/utils/json_cleaner.py
agilemind/utils/json_to_markdown.py
agilemind/utils/model_info.py
agilemind/utils/retry.py
agilemind/utils/window.py
agilemind-0.1.0.dist-info/METADATA
agilemind-0.1.0.dist-info/WHEEL
agilemind-0.1.0.dist-info/entry_points.txt
agilemind-0.1.0.dist-info/licenses/LICENSE
agilemind-0.1.0.dist-info/RECORD
