Metadata-Version: 2.4
Name: AgileMind
Version: 0.1.0
Summary: A multi-agent software development tool.
Project-URL: Homepage, https://github.com/wnrock/AgileMind
Project-URL: Issues, https://github.com/wnrock/AgileMind/issues
Author: WnRock
License-Expression: MIT
License-File: LICENSE
Classifier: Operating System :: OS Independent
Classifier: Programming Language :: Python :: 3
Requires-Python: >=3.8
Requires-Dist: altair
Requires-Dist: annotated-types
Requires-Dist: anyio
Requires-Dist: astroid
Requires-Dist: attrs
Requires-Dist: beautifulsoup4
Requires-Dist: blinker
Requires-Dist: cachetools
Requires-Dist: certifi
Requires-Dist: charset-normalizer
Requires-Dist: click
Requires-Dist: contourpy
Requires-Dist: cycler
Requires-Dist: dill
Requires-Dist: distro
Requires-Dist: esprima
Requires-Dist: fonttools
Requires-Dist: gitdb
Requires-Dist: gitpython
Requires-Dist: h11
Requires-Dist: httpcore
Requires-Dist: httpx
Requires-Dist: idna
Requires-Dist: isort
Requires-Dist: jinja2
Requires-Dist: jiter
Requires-Dist: jsonschema
Requires-Dist: jsonschema-specifications
Requires-Dist: kiwisolver
Requires-Dist: markdown-it-py
Requires-Dist: markupsafe
Requires-Dist: matplotlib
Requires-Dist: mccabe
Requires-Dist: mdurl
Requires-Dist: mypy
Requires-Dist: mypy-extensions
Requires-Dist: narwhals
Requires-Dist: networkx
Requires-Dist: numpy
Requires-Dist: openai
Requires-Dist: packaging
Requires-Dist: pandas
Requires-Dist: pillow
Requires-Dist: platformdirs
Requires-Dist: plotly
Requires-Dist: protobuf
Requires-Dist: pyarrow
Requires-Dist: pydantic
Requires-Dist: pydantic-core
Requires-Dist: pydeck
Requires-Dist: pygments
Requires-Dist: pylint
Requires-Dist: pyparsing
Requires-Dist: python-dateutil
Requires-Dist: python-dotenv
Requires-Dist: pytz
Requires-Dist: pyyaml
Requires-Dist: rdflib
Requires-Dist: readchar
Requires-Dist: referencing
Requires-Dist: regex
Requires-Dist: requests
Requires-Dist: rich
Requires-Dist: rpds-py
Requires-Dist: six
Requires-Dist: smmap
Requires-Dist: sniffio
Requires-Dist: soupsieve
Requires-Dist: streamlit
Requires-Dist: streamlit-agraph
Requires-Dist: tenacity
Requires-Dist: tiktoken
Requires-Dist: tinycss2
Requires-Dist: toml
Requires-Dist: tomlkit
Requires-Dist: tornado
Requires-Dist: tqdm
Requires-Dist: typing-extensions
Requires-Dist: tzdata
Requires-Dist: urllib3
Requires-Dist: watchdog
Requires-Dist: webencodings
